redis_redirect/__init__.py
redis_redirect/aioredis_wrapper.py
redis_redirect/pubsub.py
redis_redirect/redis_wrapper.py
redis_redirect/version.py
redis_redirect-0.1.9.dist-info/licenses/LICENSE.txt
redis_redirect-0.1.9.dist-info/METADATA
redis_redirect-0.1.9.dist-info/WHEEL
redis_redirect-0.1.9.dist-info/top_level.txt
redis_redirect-0.1.9.dist-info/RECORD
