Metadata-Version: 2.4
Name: redis-redirect
Version: 0.1.9
Summary: (aio)REDIS wrapper to deal with cluster redirect exceptions (`MOVED`).
Home-page: https://github.com/andgineer/redis-redirect
Author: Andrey Sorokin
Author-email: andrey@sorokin.engineer
Keywords: redis asyncio wrapper
Classifier: Programming Language :: Python :: 3
Classifier: License :: OSI Approved :: MIT License
Classifier: Operating System :: OS Independent
Requires-Python: >=3.8
License-File: LICENSE.txt
Requires-Dist: hiredis
Requires-Dist: types-redis
Requires-Dist: redis>=4.2.0rc1
Dynamic: author
Dynamic: author-email
Dynamic: classifier
Dynamic: description
Dynamic: description-content-type
Dynamic: home-page
Dynamic: keywords
Dynamic: license-file
Dynamic: requires-dist
Dynamic: requires-python
Dynamic: summary
